odoo10_addon_mrp_bom_component_find-10.0.1.0.0-py2.7-nspkg.pth
odoo/addons/mrp_bom_component_find/README.rst
odoo/addons/mrp_bom_component_find/__init__.py
odoo/addons/mrp_bom_component_find/__manifest__.py
odoo/addons/mrp_bom_component_find/i18n/fr.po
odoo/addons/mrp_bom_component_find/models/__init__.py
odoo/addons/mrp_bom_component_find/models/product.py
odoo/addons/mrp_bom_component_find/static/description/icon.png
odoo/addons/mrp_bom_component_find/static/description/mrp_bom_component_find.png
odoo/addons/mrp_bom_component_find/views/product_views.xml
odoo/addons/mrp_bom_component_find/wizard/__init__.py
odoo/addons/mrp_bom_component_find/wizard/mrp_bom_component_find_wizard.py
odoo/addons/mrp_bom_component_find/wizard/mrp_bom_component_find_wizard.xml
odoo10_addon_mrp_bom_component_find-10.0.1.0.0.dist-info/DESCRIPTION.rst
odoo10_addon_mrp_bom_component_find-10.0.1.0.0.dist-info/METADATA
odoo10_addon_mrp_bom_component_find-10.0.1.0.0.dist-info/RECORD
odoo10_addon_mrp_bom_component_find-10.0.1.0.0.dist-info/WHEEL
odoo10_addon_mrp_bom_component_find-10.0.1.0.0.dist-info/metadata.json
odoo10_addon_mrp_bom_component_find-10.0.1.0.0.dist-info/namespace_packages.txt
odoo10_addon_mrp_bom_component_find-10.0.1.0.0.dist-info/top_level.txt
